prinf/__init__.py
prinf-1.1.1.dist-info/METADATA
prinf-1.1.1.dist-info/WHEEL
prinf-1.1.1.dist-info/top_level.txt
prinf-1.1.1.dist-info/RECORD
